README.txt
setup.py
sun_oss/__init__.py
sun_oss/bucket.py
sun_oss/exceptions.py
sun_oss/utils.py
sun_oss.egg-info/PKG-INFO
sun_oss.egg-info/SOURCES.txt
sun_oss.egg-info/dependency_links.txt
sun_oss.egg-info/requires.txt
sun_oss.egg-info/top_level.txt