Metadata-Version: 1.0
Name: sun-oss
Version: 0.1.3
Summary: A Simple OSS SDK Integration. Include Aliyun, Qiniu, Qcloud, Maybe more
Home-page: https://github.com/PINKONG/sun-oss-python
Author: pinkong
Author-email: alain.swun@gmail.com
License: PSF
Keywords: OSS Integration Aliyun Qiniu Qcloud
Platform: UNKNOWN
